pygame_scrollbar/__init__.py
pygame_scrollbar/content_bar.py
pygame_scrollbar/scroll_bar_event_handler.py
pygame_scrollbar/scroll_bar_manager.py
pygame_scrollbar/scroll_bar_position.py
pygame_scrollbar/scroll_speed_animation_manager.py
pygame_scrollbar/scroll_speed_manager.py
pygame_scrollbar/scroll_surface_manager.py
pygame_scrollbar-1.1.0.dist-info/METADATA
pygame_scrollbar-1.1.0.dist-info/WHEEL
pygame_scrollbar-1.1.0.dist-info/top_level.txt
pygame_scrollbar-1.1.0.dist-info/RECORD
