Metadata-Version: 2.1
Name: pygame-scrollbar
Version: 1.1.0
Summary: A package for adding scrollbar to surfaces in pygame.
Home-page: https://github.com/FrickTzy/Pygame-Scrollbar
Author: FrickTzy (Kurt Arnoco)
License: UNKNOWN
Keywords: python,pygame,python game,python game development,scrollbar in pygame,python scrollbar,pygame scrollbar
Platform: UNKNOWN
